rlyehian/__init__.py
rlyehian/ainghft.py
rlyehian/kadishtuor.csv
rlyehian-0.3.dist-info/LICENSE
rlyehian-0.3.dist-info/METADATA
rlyehian-0.3.dist-info/WHEEL
rlyehian-0.3.dist-info/top_level.txt
rlyehian-0.3.dist-info/RECORD
