Metadata-Version: 2.1
Name: rlyehian
Version: 0.3
Summary: Translate to the language of the "old ones" with the serpent's tong in the digital world.
Home-page: https://github.com/JLDevOps/Rlyehian
Author: Jimmy Le (JLDevOps)
Author-email: jldevops@gmail.com
License: UNKNOWN
Platform: UNKNOWN
Classifier: Programming Language :: Python :: 3
Classifier: License :: OSI Approved :: MIT License
Classifier: Operating System :: OS Independent
